modplot/MODLogo.pdf
modplot/__init__.py
MODPlot-0.1.1.dist-info/LICENSE
MODPlot-0.1.1.dist-info/METADATA
MODPlot-0.1.1.dist-info/WHEEL
MODPlot-0.1.1.dist-info/top_level.txt
MODPlot-0.1.1.dist-info/RECORD
