Metadata-Version: 2.1
Name: MODPlot
Version: 0.1.1
Summary: Functions to create matplotlib plots in the MOD style
Home-page: https://github.com/pkomiske/MODPlot
Author: Patrick T. Komiske III
Author-email: pkomiske@mit.edu
License: GPL-3.0
Keywords: mod,plot,cms open data,matplotlib
Platform: UNKNOWN
Classifier: Development Status :: 5 - Production/Stable
Classifier: License :: OSI Approved :: GNU General Public License v3 (GPLv3)
Classifier: Natural Language :: English
Classifier: Programming Language :: Python
Classifier: Programming Language :: Python :: 3
Classifier: Programming Language :: Python :: 3 :: Only
Classifier: Programming Language :: Python :: 3.6
Classifier: Programming Language :: Python :: 3.7
Classifier: Programming Language :: Python :: 3.8
Classifier: Programming Language :: Python :: 3.9
Classifier: Topic :: Scientific/Engineering
Classifier: Topic :: Scientific/Engineering :: Physics
Classifier: Topic :: Software Development :: Libraries :: Python Modules
Requires-Python: >=3.5
Requires-Dist: matplotlib (>=3.0.0)
Requires-Dist: numpy (>=1.12.0)
Requires-Dist: PyPDF2 (>=1.26.0)
